{
    "_links": {
        "self": {
            "href": "http:\/\/localhost:8080\/slide\/177?_format=hal_json"
        },
        "type": {
            "href": "http:\/\/drupal.org\/rest\/type\/slide\/full_width_one_column"
        },
        "http:\/\/drupal.org\/rest\/relation\/slide\/full_width_one_column\/field_background_image": [
            {
                "href": "http:\/\/localhost:8080\/sites\/default\/files\/Horta-JoseRamos_HEro%20Image.jpg"
            }
        ]
    },
    "id": [
        {
            "value": 177
        }
    ],
    "uuid": [
        {
            "value": "2328b594-acf7-469e-b0bf-fe3187a864f2"
        }
    ],
    "langcode": [
        {
            "value": "en",
            "lang": "en"
        }
    ],
    "type": [
        {
            "target_id": "full_width_one_column"
        }
    ],
    "title": [
        {
            "value": "Timor-Leste: From Conflict to Resolution and Peace",
            "lang": "en"
        }
    ],
    "created": [
        {
            "value": "2020-02-13T07:45:06+00:00",
            "lang": "en",
            "format": "Y-m-d\\TH:i:sP"
        }
    ],
    "changed": [
        {
            "value": "2020-02-13T07:45:06+00:00",
            "lang": "en",
            "format": "Y-m-d\\TH:i:sP"
        }
    ],
    "default_langcode": [
        {
            "value": true,
            "lang": "en"
        }
    ],
    "metatag": [
        {
            "value": []
        }
    ],
    "field_background_color": [
        {
            "color": "#000000",
            "opacity": 1
        }
    ],
    "_embedded": {
        "http:\/\/drupal.org\/rest\/relation\/slide\/full_width_one_column\/field_background_image": [
            {
                "_links": {
                    "self": {
                        "href": "http:\/\/localhost:8080\/sites\/default\/files\/Horta-JoseRamos_HEro%20Image.jpg"
                    },
                    "type": {
                        "href": "http:\/\/drupal.org\/rest\/type\/file\/file"
                    }
                },
                "uuid": [
                    {
                        "value": "d928aa71-0477-49a0-99d8-8eb5e1858d41"
                    }
                ]
            }
        ]
    },
    "field_link": [
        {
            "uri": "\/by_uuid\/node\/bcac0f86-94aa-4a39-b4a6-0fcedb3f3458",
            "title": null,
            "options": []
        }
    ],
    "field_promoted": [
        {
            "value": false
        }
    ],
    "field_published": [
        {
            "value": true
        }
    ],
    "field_subtitle": [
        {
            "value": "Power of Ideas"
        }
    ],
    "field_text_color": [
        {
            "color": "#000000",
            "opacity": 1
        }
    ]
}