{
    "_links": {
        "self": {
            "href": "http:\/\/localhost:8080\/slide\/222?_format=hal_json"
        },
        "type": {
            "href": "http:\/\/drupal.org\/rest\/type\/slide\/full_width_one_column"
        },
        "http:\/\/drupal.org\/rest\/relation\/slide\/full_width_one_column\/field_background_image": [
            {
                "href": "http:\/\/localhost:8080\/sites\/default\/files\/Bechara_Choucair_Hero_Image.jpg"
            }
        ]
    },
    "id": [
        {
            "value": 222
        }
    ],
    "uuid": [
        {
            "value": "cc30b389-10d2-44e6-a4ca-27c4e5c6a8b6"
        }
    ],
    "langcode": [
        {
            "value": "en",
            "lang": "en"
        }
    ],
    "type": [
        {
            "target_id": "full_width_one_column"
        }
    ],
    "title": [
        {
            "value": "Removing Barriers to Aging Well",
            "lang": "en"
        }
    ],
    "created": [
        {
            "value": "2020-02-13T07:45:06+00:00",
            "lang": "en",
            "format": "Y-m-d\\TH:i:sP"
        }
    ],
    "changed": [
        {
            "value": "2020-02-13T07:45:06+00:00",
            "lang": "en",
            "format": "Y-m-d\\TH:i:sP"
        }
    ],
    "default_langcode": [
        {
            "value": true,
            "lang": "en"
        }
    ],
    "metatag": [
        {
            "value": []
        }
    ],
    "field_background_color": [
        {
            "color": "#000000",
            "opacity": 1
        }
    ],
    "_embedded": {
        "http:\/\/drupal.org\/rest\/relation\/slide\/full_width_one_column\/field_background_image": [
            {
                "_links": {
                    "self": {
                        "href": "http:\/\/localhost:8080\/sites\/default\/files\/Bechara_Choucair_Hero_Image.jpg"
                    },
                    "type": {
                        "href": "http:\/\/drupal.org\/rest\/type\/file\/file"
                    }
                },
                "uuid": [
                    {
                        "value": "aabf1039-0c98-4a07-87f8-174b73b38005"
                    }
                ]
            }
        ]
    },
    "field_link": [
        {
            "uri": "\/by_uuid\/node\/00708977-1baa-43ff-8152-312ace8b106d",
            "title": null,
            "options": []
        }
    ],
    "field_promoted": [
        {
            "value": false
        }
    ],
    "field_published": [
        {
            "value": true
        }
    ],
    "field_subtitle": [
        {
            "value": "Power of Ideas - Future of Health Summit 2019"
        }
    ],
    "field_text_color": [
        {
            "color": "#000000",
            "opacity": 1
        }
    ]
}