{
    "_links": {
        "self": {
            "href": ""
        },
        "type": {
            "href": "http:\/\/drupal.org\/rest\/type\/path_alias\/path_alias"
        }
    },
    "id": [
        {
            "value": 654
        }
    ],
    "uuid": [
        {
            "value": "44728ce4-6e55-49d3-94b7-951a9144fe1e"
        }
    ],
    "revision_id": [
        {
            "value": 654
        }
    ],
    "langcode": [
        {
            "value": "en"
        }
    ],
    "path": [
        {
            "value": "\/node\/601"
        }
    ],
    "alias": [
        {
            "value": "\/article\/how-cities-and-older-adults-can-improve-health-together"
        }
    ],
    "status": [
        {
            "value": true
        }
    ]
}