{
    "_links": {
        "self": {
            "href": ""
        },
        "type": {
            "href": "http:\/\/drupal.org\/rest\/type\/path_alias\/path_alias"
        }
    },
    "id": [
        {
            "value": 579
        }
    ],
    "uuid": [
        {
            "value": "4ecc95bf-3400-4419-8333-67a71e88672c"
        }
    ],
    "revision_id": [
        {
            "value": 579
        }
    ],
    "langcode": [
        {
            "value": "en"
        }
    ],
    "path": [
        {
            "value": "\/node\/526"
        }
    ],
    "alias": [
        {
            "value": "\/article\/financial-inclusion-platform-prosper"
        }
    ],
    "status": [
        {
            "value": true
        }
    ]
}