{
    "_links": {
        "self": {
            "href": ""
        },
        "type": {
            "href": "http:\/\/drupal.org\/rest\/type\/path_alias\/path_alias"
        }
    },
    "id": [
        {
            "value": 578
        }
    ],
    "uuid": [
        {
            "value": "85b596ea-ead7-492e-ac60-75ee25ba1121"
        }
    ],
    "revision_id": [
        {
            "value": 578
        }
    ],
    "langcode": [
        {
            "value": "en"
        }
    ],
    "path": [
        {
            "value": "\/node\/525"
        }
    ],
    "alias": [
        {
            "value": "\/article\/towards-mixed-society-dream-humanity"
        }
    ],
    "status": [
        {
            "value": true
        }
    ]
}