{
    "_links": {
        "self": {
            "href": ""
        },
        "type": {
            "href": "http:\/\/drupal.org\/rest\/type\/path_alias\/path_alias"
        }
    },
    "id": [
        {
            "value": 309
        }
    ],
    "uuid": [
        {
            "value": "8eae53e6-071c-412c-b499-187df89e5f0a"
        }
    ],
    "revision_id": [
        {
            "value": 309
        }
    ],
    "langcode": [
        {
            "value": "en"
        }
    ],
    "path": [
        {
            "value": "\/node\/256"
        }
    ],
    "alias": [
        {
            "value": "\/article\/3rd-annual-forbes-milken-institute-best-places-ranking-shows-top-cities-do-business-advance"
        }
    ],
    "status": [
        {
            "value": true
        }
    ]
}