{
    "_links": {
        "self": {
            "href": ""
        },
        "type": {
            "href": "http:\/\/drupal.org\/rest\/type\/path_alias\/path_alias"
        }
    },
    "id": [
        {
            "value": 110
        }
    ],
    "uuid": [
        {
            "value": "b0ab50f8-1aea-45cc-8bc1-d5b523ea76e9"
        }
    ],
    "revision_id": [
        {
            "value": 110
        }
    ],
    "langcode": [
        {
            "value": "en"
        }
    ],
    "path": [
        {
            "value": "\/node\/57"
        }
    ],
    "alias": [
        {
            "value": "\/article\/where-does-your-city-rank-milken-institute-index-analyses-352-metropolitan-areas-identify"
        }
    ],
    "status": [
        {
            "value": true
        }
    ]
}