{
    "_links": {
        "self": {
            "href": ""
        },
        "type": {
            "href": "http:\/\/drupal.org\/rest\/type\/path_alias\/path_alias"
        }
    },
    "id": [
        {
            "value": 81
        }
    ],
    "uuid": [
        {
            "value": "e6074e58-3e09-464a-8f36-9984602ccaac"
        }
    ],
    "revision_id": [
        {
            "value": 81
        }
    ],
    "langcode": [
        {
            "value": "en"
        }
    ],
    "path": [
        {
            "value": "\/node\/28"
        }
    ],
    "alias": [
        {
            "value": "\/article\/one-fix-greater-social-mobility-us-early-interventions"
        }
    ],
    "status": [
        {
            "value": true
        }
    ]
}