{
    "_links": {
        "self": {
            "href": "http:\/\/localhost:8080\/sites\/default\/files\/oembed_thumbnails\/2tAkcUKucz-yI5UGEj5IxcJkGkKapxQBDc6mR2yo4vE.jpg"
        },
        "type": {
            "href": "http:\/\/drupal.org\/rest\/type\/file\/file"
        },
        "http:\/\/drupal.org\/rest\/relation\/file\/file\/uid": [
            {
                "href": "http:\/\/localhost:8080\/user\/2?_format=hal_json"
            }
        ]
    },
    "fid": [
        {
            "value": 1235
        }
    ],
    "uuid": [
        {
            "value": "1e1f53dc-875b-4080-a7dc-4925f66b9a18"
        }
    ],
    "langcode": [
        {
            "value": "en"
        }
    ],
    "_embedded": {
        "http:\/\/drupal.org\/rest\/relation\/file\/file\/uid": [
            {
                "_links": {
                    "self": {
                        "href": "http:\/\/localhost:8080\/user\/2?_format=hal_json"
                    },
                    "type": {
                        "href": "http:\/\/drupal.org\/rest\/type\/user\/user"
                    }
                },
                "uuid": [
                    {
                        "value": "20b60d4b-bf21-4da9-8d41-4af6bd4e47ba"
                    }
                ]
            }
        ]
    },
    "filename": [
        {
            "value": "2tAkcUKucz-yI5UGEj5IxcJkGkKapxQBDc6mR2yo4vE.jpg"
        }
    ],
    "uri": [
        {
            "value": "public:\/\/oembed_thumbnails\/2tAkcUKucz-yI5UGEj5IxcJkGkKapxQBDc6mR2yo4vE.jpg",
            "url": "\/sites\/default\/files\/oembed_thumbnails\/2tAkcUKucz-yI5UGEj5IxcJkGkKapxQBDc6mR2yo4vE.jpg"
        }
    ],
    "filemime": [
        {
            "value": "image\/jpeg"
        }
    ],
    "filesize": [
        {
            "value": 21514
        }
    ],
    "status": [
        {
            "value": true
        }
    ],
    "created": [
        {
            "value": "2020-02-13T07:30:47+00:00",
            "format": "Y-m-d\\TH:i:sP"
        }
    ],
    "changed": [
        {
            "value": "2020-02-13T07:30:47+00:00",
            "format": "Y-m-d\\TH:i:sP"
        }
    ]
}