{
    "_links": {
        "self": {
            "href": "http:\/\/localhost:8080\/sites\/default\/files\/oembed_thumbnails\/3j1215LUn5IMbvBAWHLSfAAm029_LccIPy_g5NxmGRg.jpg"
        },
        "type": {
            "href": "http:\/\/drupal.org\/rest\/type\/file\/file"
        },
        "http:\/\/drupal.org\/rest\/relation\/file\/file\/uid": [
            {
                "href": "http:\/\/localhost:8080\/user\/2?_format=hal_json"
            }
        ]
    },
    "fid": [
        {
            "value": 1812
        }
    ],
    "uuid": [
        {
            "value": "9159a2a9-8a86-435f-bca0-bc8f7a021e77"
        }
    ],
    "langcode": [
        {
            "value": "en"
        }
    ],
    "_embedded": {
        "http:\/\/drupal.org\/rest\/relation\/file\/file\/uid": [
            {
                "_links": {
                    "self": {
                        "href": "http:\/\/localhost:8080\/user\/2?_format=hal_json"
                    },
                    "type": {
                        "href": "http:\/\/drupal.org\/rest\/type\/user\/user"
                    }
                },
                "uuid": [
                    {
                        "value": "20b60d4b-bf21-4da9-8d41-4af6bd4e47ba"
                    }
                ]
            }
        ]
    },
    "filename": [
        {
            "value": "3j1215LUn5IMbvBAWHLSfAAm029_LccIPy_g5NxmGRg.jpg"
        }
    ],
    "uri": [
        {
            "value": "public:\/\/oembed_thumbnails\/3j1215LUn5IMbvBAWHLSfAAm029_LccIPy_g5NxmGRg.jpg",
            "url": "\/sites\/default\/files\/oembed_thumbnails\/3j1215LUn5IMbvBAWHLSfAAm029_LccIPy_g5NxmGRg.jpg"
        }
    ],
    "filemime": [
        {
            "value": "image\/jpeg"
        }
    ],
    "filesize": [
        {
            "value": 23147
        }
    ],
    "status": [
        {
            "value": true
        }
    ],
    "created": [
        {
            "value": "2020-02-13T07:30:47+00:00",
            "format": "Y-m-d\\TH:i:sP"
        }
    ],
    "changed": [
        {
            "value": "2020-02-13T07:30:47+00:00",
            "format": "Y-m-d\\TH:i:sP"
        }
    ]
}